xicsrt_contrib/__init__.py
xicsrt_contrib/_version.py
xicsrt_contrib/filters/__init__.py
xicsrt_contrib/optics/__init__.py
xicsrt_contrib/sources/_XicsrtPlasmaImas.py
xicsrt_contrib/sources/_XicsrtPlasmaVmec.py
xicsrt_contrib/sources/_XicsrtPlasmaVmecDatafile.py
xicsrt_contrib/sources/__init__.py
xicsrt_contrib-0.7.0.dist-info/AUTHORS
xicsrt_contrib-0.7.0.dist-info/LICENSE
xicsrt_contrib-0.7.0.dist-info/METADATA
xicsrt_contrib-0.7.0.dist-info/WHEEL
xicsrt_contrib-0.7.0.dist-info/top_level.txt
xicsrt_contrib-0.7.0.dist-info/RECORD
