Metadata-Version: 2.1
Name: xicsrt-contrib
Version: 0.7.0
Summary: Contributed modules for the xicsrt raytracing code.
Home-page: https://github.com/PrincetonUniversity/xicsrt_contrib
Author: Novimir Antoniuk Pablant
Author-email: npablant@pppl.gov
Maintainer: Novimir Antoniuk Pablant
Maintainer-email: npablant@pppl.gov
License: MIT
Platform: UNKNOWN
Classifier: Development Status :: 4 - Beta
Classifier: License :: OSI Approved :: MIT License
Classifier: Programming Language :: Python :: 3
Classifier: Operating System :: OS Independent
Requires-Python: >=3.8
License-File: LICENSE
License-File: AUTHORS
Requires-Dist: xicsrt
